{
    "apiVersion": "1.0",
    "serverId": "IAC_CLUSTER",
    "products": [
        {
            "id": "PDS_KICS",
            "path": "/pds/scripts/kics.sh",
            "scanType": "codeScan",
            "description": "Runs the Infrastructure-as-Code security checker Kics."
        },
        {
            "id": "PDS_KICS_MOCK",
            "path": "/pds/scripts/kics_mock.sh",
            "scanType": "codeScan",
            "description": "Runs Kics mock. It returns a fixed result file."
        }
    ]
}
